README.rst
setup.py
zgh0241/__init__.py
zgh0241/autotest.py
zgh0241/config.py
zgh0241/data.py
zgh0241/database.py
zgh0241/elements.py
zgh0241/globals.py
zgh0241/junit.py
zgh0241/locator.py
zgh0241/log.py
zgh0241/parse.py
zgh0241/report.py
zgh0241/snapshot.py
zgh0241/testcase.py
zgh0241/testsuite.py
zgh0241/utility.py
zgh0241/windows.py
zgh0241.egg-info/PKG-INFO
zgh0241.egg-info/SOURCES.txt
zgh0241.egg-info/dependency_links.txt
zgh0241.egg-info/requires.txt
zgh0241.egg-info/top_level.txt
zgh0241/keywords/__init__.py
zgh0241/keywords/common.py
zgh0241/keywords/http.py
zgh0241/keywords/mobile.py
zgh0241/keywords/web.py
zgh0241/lib/__init__.py
zgh0241/lib/c.py
zgh0241/lib/http_handle.py
zgh0241/lib/u.py