Metadata-Version: 1.0
Name: zgh0241
Version: 1.0.0
Summary: 基于Python+Selenium的UI自动化测试框架
Home-page: https://github.com/zgh0241/zgh0241
Author: zgh
Author-email: 18857757067@163.com
License: BSD License
Platform: all
